[
  {
    "question": "What is the primary purpose of a surgical drain?",
    "answer": "It helps remove fluids and prevent infection after surgery."
  },
  {
    "question": "What is the most common cause of postoperative fever within 24 hours?",
    "answer": "It is usually caused by lung atelectasis formation."
  },
  {
    "question": "What is the universal sign of acute appendicitis?",
    "answer": "Pain in the right lower abdomen at McBurney's point."
  },
  {
    "question": "What is the preferred imaging method for gallstones?",
    "answer": "Gallstones are most often detected using ultrasound imaging."
  },
  {
    "question": "Which suture material is absorbable and often used in internal tissues?",
    "answer": "Vicryl is an absorbable synthetic suture material."
  },
  {
    "question": "What is the first step in controlling external hemorrhage?",
    "answer": "Apply firm direct pressure to the bleeding area immediately."
  },
  {
    "question": "What is the primary indication for a tracheostomy?",
    "answer": "It is used to secure a patient’s airway safely."
  },
  {
    "question": "What does the 'Rule of Nines' estimate?",
    "answer": "It calculates the burned body surface area percentage."
  },
  {
    "question": "What is the surgical term for removal of the gallbladder?",
    "answer": "This surgical procedure is called cholecystectomy operation."
  },
  {
    "question": "What is the classic triad of symptoms in Charcot's triad?",
    "answer": "Fever, jaundice, and pain in the right upper abdomen."
  },
  {
    "question": "Which antibiotic is commonly used for preoperative prophylaxis in clean-contaminated surgeries?",
    "answer": "Cefazolin is often given before surgery to prevent infection."
  },
  {
    "question": "What is the common complication of deep vein thrombosis after surgery?",
    "answer": "It can lead to a dangerous pulmonary embolism formation."
  },
  {
    "question": "What type of hernia passes through Hesselbach's triangle?",
    "answer": "A direct inguinal hernia passes through Hesselbach's triangle."
  },
  {
    "question": "What is the most common site for colorectal cancer?",
    "answer": "It is most frequently found in the rectosigmoid region."
  },
  {
    "question": "What is the primary treatment for tension pneumothorax?",
    "answer": "Needle decompression is followed by chest tube insertion procedure."
  },
  {
    "question": "What is the most common cause of small bowel obstruction?",
    "answer": "Postoperative scar tissue adhesions are the leading cause."
  },
  {
    "question": "What is the Glasgow Coma Scale used for?",
    "answer": "It measures a patient’s level of consciousness after injury."
  },
  {
    "question": "What surgical procedure is done to remove part of the colon?",
    "answer": "The procedure is called a colectomy or colon resection."
  },
  {
    "question": "What is the name of the surgical instrument used to hold tissue edges apart?",
    "answer": "A retractor is used to hold tissues open during surgery."
  },
  {
    "question": "What is the term for surgical removal of the spleen?",
    "answer": "This operation is medically referred to as splenectomy procedure."
  }
]
